futured/__init__.py
futured/py.typed
futured-1.5.dist-info/LICENSE.txt
futured-1.5.dist-info/METADATA
futured-1.5.dist-info/WHEEL
futured-1.5.dist-info/top_level.txt
futured-1.5.dist-info/RECORD
