Metadata-Version: 2.1
Name: futured
Version: 1.5
Summary: Functional interface for concurrent futures, including async coroutines.
Author-email: Aric Coady <aric.coady@gmail.com>
License: Copyright 2022 Aric Coady
Project-URL: Homepage, https://github.com/coady/futured
Project-URL: Documentation, https://coady.github.io/futured
Project-URL: Changelog, https://github.com/coady/futured/blob/main/CHANGELOG.md
Project-URL: Issues, https://github.com/coady/futured/issues
Keywords: concurrent,futures,threads,processes,async,asyncio
Classifier: Development Status :: 5 - Production/Stable
Classifier: Framework :: AsyncIO
Classifier: Intended Audience :: Developers
Classifier: License :: OSI Approved :: Apache Software License
Classifier: Operating System :: OS Independent
Classifier: Programming Language :: Python :: 3
Classifier: Programming Language :: Python :: 3.9
Classifier: Programming Language :: Python :: 3.10
Classifier: Programming Language :: Python :: 3.11
Classifier: Programming Language :: Python :: 3.12
Classifier: Programming Language :: Python :: 3.13
Classifier: Topic :: Software Development :: Libraries :: Python Modules
Classifier: Typing :: Typed
Requires-Python: >=3.9
License-File: LICENSE.txt
